fuzzy_sequence_matcher/__init__.py
fuzzy_sequence_matcher/fuzzy_sequence_matcher.py
fuzzy_sequence_matcher-0.1.1.dist-info/AUTHORS.rst
fuzzy_sequence_matcher-0.1.1.dist-info/LICENSE
fuzzy_sequence_matcher-0.1.1.dist-info/METADATA
fuzzy_sequence_matcher-0.1.1.dist-info/WHEEL
fuzzy_sequence_matcher-0.1.1.dist-info/top_level.txt
fuzzy_sequence_matcher-0.1.1.dist-info/zip-safe
fuzzy_sequence_matcher-0.1.1.dist-info/RECORD
