Metadata-Version: 2.1
Name: fuzzy-sequence-matcher
Version: 0.1.1
Summary: Finds best pairings of elements between two sequences
Home-page: https://github.com/catherinedevlin/fuzzy_sequence_matcher
Author: Catherine Devlin
Author-email: catherine.devlin@gmail.com
License: MIT license
Platform: UNKNOWN
Classifier: Development Status :: 2 - Pre-Alpha
Classifier: Intended Audience :: Developers
Classifier: License :: OSI Approved :: MIT License
Classifier: Natural Language :: English
Classifier: Programming Language :: Python :: 3
Classifier: Programming Language :: Python :: 3.6
Classifier: Programming Language :: Python :: 3.7
Classifier: Programming Language :: Python :: 3.8
Requires-Python: >=3.6
